web_queue/VERSION
web_queue/__init__.py
web_queue/app.py
web_queue/client/__init__.py
web_queue/client/_client.py
web_queue/client/ai/__init__.py
web_queue/client/ai/_ai.py
web_queue/client/clean/__init__.py
web_queue/client/clean/_clean.py
web_queue/client/config.py
web_queue/client/web/__init__.py
web_queue/client/web/_web.py
web_queue/config.py
web_queue/types/__init__.py
web_queue/types/fetch_html_message.py
web_queue/types/html_content.py
web_queue/types/html_metadata_response.py
web_queue/types/message.py
web_queue/types/step_callback.py
web_queue/utils/__init__.py
web_queue/utils/compression.py
web_queue/utils/html_cleaner.py
web_queue/utils/html_to_str.py
web_queue/utils/human_delay.py
web_queue/utils/page_with_init_script.py
web_queue/utils/simulate_mouse_circling.py
web_queue/utils/simulate_scrolling.py
web_queue2-0.2.0.dist-info/METADATA
web_queue2-0.2.0.dist-info/WHEEL
web_queue2-0.2.0.dist-info/licenses/LICENSE
web_queue2-0.2.0.dist-info/RECORD
